StructureCloud/Datasets/__init__.py
StructureCloud/Datasets/preprocess.py
StructureCloud/Datasets/retrieval.py
structurecloud-0.0.1.dist-info/licenses/LICENSE
structurecloud-0.0.1.dist-info/METADATA
structurecloud-0.0.1.dist-info/WHEEL
structurecloud-0.0.1.dist-info/top_level.txt
structurecloud-0.0.1.dist-info/RECORD
