Metadata-Version: 2.4
Name: StructureCloud
Version: 0.0.1
Summary: Standard formating and easy access to 3D structural datasets for machine learning. currently under development...
Author-email: Ty Perez <ty.jperez@gmail.com>
License-Expression: MIT
Project-URL: Homepage, https://github.com/TyJPerez/StructureCloud
Project-URL: Issues, https://github.com/TyJPerez/StructureCloud/issues
Classifier: Programming Language :: Python :: 3
Classifier: Operating System :: OS Independent
Requires-Python: >=3.9
License-File: LICENSE
Dynamic: license-file
